sunbird/__init__.py
sunbird/categorical_encoding.py
sunbird/feature_selection.py
sunbird/nan_values.py
sunbird/outliers.py
sunbird/transformation.py
sunbird-0.0.4.dist-info/LICENSE
sunbird-0.0.4.dist-info/METADATA
sunbird-0.0.4.dist-info/WHEEL
sunbird-0.0.4.dist-info/top_level.txt
sunbird-0.0.4.dist-info/RECORD
