Metadata-Version: 2.1
Name: sunbird
Version: 0.0.4
Summary: UNKNOWN
Home-page: http://www.sunbird.ml
Author: ['Vivek Pisal', 'Vaishnavi Ghadge']
Author-email: vivekpisal12345@gmail.com
License: UNKNOWN
Platform: UNKNOWN
Classifier: Programming Language :: Python :: 3
Classifier: License :: OSI Approved :: MIT License
Classifier: Operating System :: OS Independent
Requires-Python: >=3.6
Requires-Dist: pandas
Requires-Dist: numpy
Requires-Dist: sklearn
Requires-Dist: scipy
Requires-Dist: seaborn
